sstCloud/__init__.py
sstCloudClient-0.0.1.dist-info/DESCRIPTION.rst
sstCloudClient-0.0.1.dist-info/METADATA
sstCloudClient-0.0.1.dist-info/RECORD
sstCloudClient-0.0.1.dist-info/WHEEL
sstCloudClient-0.0.1.dist-info/metadata.json
sstCloudClient-0.0.1.dist-info/top_level.txt
